cloudflare_dynamic_dns
