Metadata-Version: 2.1
Name: cloudflare-dynamic-dns-client
Version: 0.2.2
Summary: Allows selfhosting on cloudflare with a dynamic ip address
Home-page: https://github.com/Littlewhinging/cloudflare-dynamic-dns
Author: Littlewhinging
License: MIT
License-File: LICENSE
Requires-Dist: cloudflare==2.11.1
Requires-Dist: requests==2.31.0
